pytest_azurepipelines.py
pytest_azurepipelines-1.0.5.data/data/resources/style.css
pytest_azurepipelines-1.0.5.dist-info/LICENSE
pytest_azurepipelines-1.0.5.dist-info/METADATA
pytest_azurepipelines-1.0.5.dist-info/WHEEL
pytest_azurepipelines-1.0.5.dist-info/entry_points.txt
pytest_azurepipelines-1.0.5.dist-info/top_level.txt
pytest_azurepipelines-1.0.5.dist-info/RECORD
