Metadata-Version: 2.1
Name: pytest-azurepipelines
Version: 1.0.5
Summary: Formatting PyTest output for Azure Pipelines UI
Home-page: https://github.com/Azure/pytest-azurepipelines
Author: Anthony Shaw
Author-email: anthonyshaw@apache.org
Maintainer: Anthony Shaw
Maintainer-email: anthonyshaw@apache.org
License: MIT
Platform: UNKNOWN
Classifier: Development Status :: 5 - Production/Stable
Classifier: Framework :: Pytest
Classifier: Intended Audience :: Developers
Classifier: Topic :: Software Development :: Testing
Classifier: Programming Language :: Python
Classifier: Programming Language :: Python :: 3
Classifier: Programming Language :: Python :: 3.5
Classifier: Programming Language :: Python :: 3.6
Classifier: Programming Language :: Python :: 3.7
Classifier: Programming Language :: Python :: 3.8
Classifier: Programming Language :: Python :: 3.9
Classifier: Programming Language :: Python :: 3.10
Classifier: Programming Language :: Python :: 3.11
Classifier: Programming Language :: Python :: 3.12
Classifier: Programming Language :: Python :: Implementation :: CPython
Classifier: Programming Language :: Python :: Implementation :: PyPy
Classifier: Operating System :: OS Independent
Classifier: License :: OSI Approved :: MIT License
Requires-Python: >=3.5
Requires-Dist: importlib-resources
Requires-Dist: pytest (>=5.0.0)
Requires-Dist: pytest-nunit (<2.0.0,>=1.0.0)
